smaj_kyber/__init__.py
smaj_kyber/core.py
smaj_kyber/lib/libkyber1024.dll
smaj_kyber/lib/libkyber1024.so
smaj_kyber/lib/libkyber1024_arm64.so
smaj_kyber/lib/libkyber1024_armv7.so
smaj_kyber/lib/libkyber1024_universal.dylib
smaj_kyber/lib/libkyber512.dll
smaj_kyber/lib/libkyber512.so
smaj_kyber/lib/libkyber512_arm64.so
smaj_kyber/lib/libkyber512_armv7.so
smaj_kyber/lib/libkyber512_universal.dylib
smaj_kyber/lib/libkyber768.dll
smaj_kyber/lib/libkyber768.so
smaj_kyber/lib/libkyber768_arm64.dylib
smaj_kyber/lib/libkyber768_arm64.so
smaj_kyber/lib/libkyber768_armv7.so
smaj_kyber/lib/libkyber768_universal.dylib
smaj_kyber-0.1.3.dist-info/licenses/LICENSE
smaj_kyber-0.1.3.dist-info/METADATA
smaj_kyber-0.1.3.dist-info/WHEEL
smaj_kyber-0.1.3.dist-info/top_level.txt
smaj_kyber-0.1.3.dist-info/RECORD
