Metadata-Version: 2.4
Name: smaj_kyber
Version: 0.1.3
Summary: Kyber KEM wrapper using ctypes and platform-specific dynamic libraries
Author: Yinka John Adegoke
License: MIT
Classifier: Programming Language :: Python :: 3
Classifier: Operating System :: OS Independent
Requires-Python: >=3.6
License-File: LICENSE
Dynamic: author
Dynamic: classifier
Dynamic: description
Dynamic: description-content-type
Dynamic: license
Dynamic: license-file
Dynamic: requires-python
Dynamic: summary
